README.rst
setup.cfg
setup.py
sepacbi/__init__.py
sepacbi/account.py
sepacbi/bank.py
sepacbi/cbibon_dom.py
sepacbi/cbibon_for.py
sepacbi/entity.py
sepacbi/iban.py
sepacbi/iban_structures.py
sepacbi/payment.py
sepacbi/records.py
sepacbi/rmtinfo.py
sepacbi/transaction.py
sepacbi/util.py
sepacbi.egg-info/PKG-INFO
sepacbi.egg-info/SOURCES.txt
sepacbi.egg-info/dependency_links.txt
sepacbi.egg-info/requires.txt
sepacbi.egg-info/top_level.txt
sepacbi.egg-info/zip-safe
tests/__init__.py
tests/definitions.py
tests/test_api.py
tests/test_cbi_output.py
tests/test_xml_output.py