Metadata-Version: 1.1
Name: sepacbi
Version: 0.1.7
Summary: SEPA Credit Transfer request (CBI) XML generator
Home-page: http://github.com/puccia/sepacbi/
Author: Emanuele Pucciarelli
Author-email: ep@corp.it
License: 3-clause BSD
Download-URL: http://github.com/puccia/sepacbi/
Keywords: xml finance banking payments
Platform: All
Classifier: Development Status :: 3 - Alpha
Classifier: Intended Audience :: Financial and Insurance Industry
Classifier: License :: OSI Approved :: BSD License
Classifier: Programming Language :: Python :: 2
Classifier: Programming Language :: Python :: 3
Classifier: Topic :: Office/Business :: Financial
